histmp-0.0.5.dist-info/top_level.txt
histmp-0.0.5.dist-info/METADATA
histmp-0.0.5.dist-info/WHEEL
histmp-0.0.5.dist-info/RECORD
histmp/__init__.py
histmp/_CPP.cpython-38-x86_64-linux-gnu.so
histmp/_CPP_PB.cpython-38-x86_64-linux-gnu.so
histmp/.libs/libgomp-f7e03b3e.so.1.0.0
