Metadata-Version: 2.1
Name: histmp
Version: 0.0.5
Summary: Calculate histograms with blazing speed.
Home-page: https://git.sr.ht/~ddavis/histmp
Author: Doug Davis
Author-email: ddavis@ddavis.io
License: BSD 3-clause
Platform: UNKNOWN
Classifier: Programming Language :: Python :: 3 :: Only
Classifier: Programming Language :: Python :: 3.6
Classifier: Programming Language :: Python :: 3.7
Classifier: Programming Language :: Python :: 3.8
Classifier: Programming Language :: C
Classifier: Programming Language :: C++
Classifier: Operating System :: MacOS
Classifier: Operating System :: POSIX
Classifier: Operating System :: POSIX :: Linux
Classifier: License :: OSI Approved :: BSD License
Classifier: Development Status :: 2 - Pre-Alpha
Classifier: Intended Audience :: Science/Research
Requires-Python: >=3.6
